koko_pkg/__init__.py
koko_pkg/initialize_koko.py
koko_pkg/koko.py
koko_cli-0.1.1.dist-info/METADATA
koko_cli-0.1.1.dist-info/WHEEL
koko_cli-0.1.1.dist-info/entry_points.txt
koko_cli-0.1.1.dist-info/top_level.txt
koko_cli-0.1.1.dist-info/RECORD
